[
  {
    "key": "S1",
    "title": "Fly ball to CF (R:1, O:1)",
    "desc": "Fly ball to Center Field, runner on 1st, no outs.",
    "outs": 1,
    "runnersOn": {
      "first": true,
      "second": false,
      "third": false
    },
    "starts": {
      "P": {
        "x": 1517,
        "y": 1461
      },
      "C": {
        "x": 1962,
        "y": 1826
      },
      "1B": {
        "x": 1875,
        "y": 1535
      },
      "2B": {
        "x": 1529,
        "y": 1155
      },
      "SS": {
        "x": 1494,
        "y": 934
      },
      "3B": {
        "x": 1096,
        "y": 1535
      },
      "LF": {
        "x": 1182,
        "y": 425
      },
      "CF": {
        "x": 1631,
        "y": 592
      },
      "RF": {
        "x": 2196,
        "y": 1212
      }
    },
    "targets": {
      "P": {
        "x": 1518,
        "y": 1472,
        "tol": 65
      },
      "C": {
        "x": 1917,
        "y": 1807,
        "tol": 97
      },
      "1B": {
        "x": 1869,
        "y": 1571,
        "tol": 65
      },
      "2B": {
        "x": 1497,
        "y": 1191,
        "tol": 65
      },
      "SS": {
        "x": 1509,
        "y": 916,
        "tol": 110
      },
      "3B": {
        "x": 1135,
        "y": 1568,
        "tol": 65
      },
      "LF": {
        "x": 1162,
        "y": 463,
        "tol": 110
      },
      "CF": {
        "x": 1643,
        "y": 631,
        "tol": 65
      },
      "RF": {
        "x": 2253,
        "y": 1211,
        "tol": 106
      }
    },
    "hit": {
      "x": 1632,
      "y": 647
    },
    "hitType": "popup",
    "batterAdvance": 2
  },
  {
    "key": "S2",
    "title": "Grounder to 1B (R1)",
    "desc": "Runner on 1B and 3B; corners in.",
    "outs": 0,
    "runnersOn": {
      "first": false,
      "second": false,
      "third": false
    },
    "starts": {
      "P": {
        "x": 1500,
        "y": 1631
      },
      "C": {
        "x": 1503,
        "y": 2147
      },
      "1B": {
        "x": 1858,
        "y": 1541
      },
      "2B": {
        "x": 1768,
        "y": 1116
      },
      "SS": {
        "x": 1156,
        "y": 1143
      },
      "3B": {
        "x": 1145,
        "y": 1536
      },
      "LF": {
        "x": 742,
        "y": 790
      },
      "CF": {
        "x": 1466,
        "y": 482
      },
      "RF": {
        "x": 2273,
        "y": 772
      }
    },
    "targets": {
      "P": {
        "x": 1560,
        "y": 1592,
        "tol": 65
      },
      "C": {
        "x": 1500,
        "y": 1915,
        "tol": 65
      },
      "1B": {
        "x": 2252,
        "y": 1364,
        "tol": 65
      },
      "2B": {
        "x": 1770,
        "y": 1368,
        "tol": 65
      },
      "SS": {
        "x": 1260,
        "y": 1393,
        "tol": 65
      },
      "3B": {
        "x": 600,
        "y": 1666,
        "tol": 65
      },
      "LF": {
        "x": 780,
        "y": 995,
        "tol": 65
      },
      "CF": {
        "x": 1500,
        "y": 771,
        "tol": 65
      },
      "RF": {
        "x": 2340,
        "y": 870,
        "tol": 65
      }
    },
    "hit": {
      "x": 1081,
      "y": 709
    },
    "hitType": "grounder",
    "batterAdvance": 1
  }
]
